qgsgl/__init__.py
qgsgl/style.py
qgsgl/utils.py
qgsgl/converters/__init__.py
qgsgl/converters/layer.py
qgsgl/expression/__init__.py
qgsgl/expression/base.py
qgsgl/expression/expression.py
qgsgl/glyphs/__init__.py
qgsgl/glyphs/default.py
qgsgl/glyphs/library.py
qgsgl/layer/__init__.py
qgsgl/layer/base.py
qgsgl/layer/circlelayer.py
qgsgl/layer/filllayer.py
qgsgl/layer/labellayer.py
qgsgl/layer/linelayer.py
qgsgl/layer/mock.py
qgsgl/layer/symbollayer.py
qgsgl/legend/__init__.py
qgsgl/legend/legend.py
qgsgl/legend/legenditem.py
qgsgl/sources/__init__.py
qgsgl/sources/base.py
qgsgl/sources/exceptions.py
qgsgl/sources/geojson.py
qgsgl/sources/vector.py
qgsgl/sprite/__init__.py
qgsgl/sprite/sprite.py
qgsgl/sprite/spriteimage.py
qgsgl/sprite/spritepixmap.py
qgsgl/symbol/__init__.py
qgsgl/symbol/base.py
qgsgl/symbol/symbol.py
qgsgl/tests/__init__.py
qgsgl/tests/test_circle_layer.py
qgsgl/tests/test_fill_layer.py
qgsgl/tests/test_font.py
qgsgl/tests/test_geojson_source.py
qgsgl/tests/test_label_layer.py
qgsgl/tests/test_layer_converter.py
qgsgl/tests/test_legend.py
qgsgl/tests/test_legend_item.py
qgsgl/tests/test_line_layer.py
qgsgl/tests/test_sprite.py
qgsgl/tests/test_sprite_image.py
qgsgl/tests/test_sprite_pixmap.py
qgsgl/tests/test_symbol_layer.py
qgsgl/tests/test_vector_source.py
qgsgl/tests/utils.py
qgsgl/tests/testdata/building.geojson
qgsgl/tests/testdata/building.gml
qgsgl/tests/testdata/building.xsd
qgsgl/tests/testdata/station.geojson
qgsgl/tests/testdata/station.gml
qgsgl/tests/testdata/station.xsd
qgsgl/tests/testdata/street.geojson
qgsgl/tests/testdata/street.gml
qgsgl/tests/testdata/street.xsd
qgsgl-0.1.2.dist-info/LICENSE.md
qgsgl-0.1.2.dist-info/METADATA
qgsgl-0.1.2.dist-info/WHEEL
qgsgl-0.1.2.dist-info/top_level.txt
qgsgl-0.1.2.dist-info/RECORD
