Metadata-Version: 2.1
Name: qgsgl
Version: 0.1.2
Summary: Convert QGIS project into webmapgl style
Home-page: https://ccrpc.org/programs/transportation/
Author: Edmond Lai
Author-email: klai@ccrpc.org
License: UNKNOWN
Keywords: QGIS gl
Platform: UNKNOWN
Classifier: Development Status :: 3 - Alpha
Classifier: Environment :: Win32 (MS Windows)
Classifier: Intended Audience :: Developers
Classifier: License :: OSI Approved :: BSD License
Classifier: Topic :: Database
Classifier: Topic :: Scientific/Engineering :: GIS
Classifier: Programming Language :: Python :: 3.6
